zbspy/__init__.py
zbspy/address.py
zbspy/asset.py
zbspy/crypto.py
zbspy/order.py
zbspy-0.16.2.dist-info/METADATA
zbspy-0.16.2.dist-info/WHEEL
zbspy-0.16.2.dist-info/top_level.txt
zbspy-0.16.2.dist-info/RECORD
