Metadata-Version: 2.1
Name: zbspy
Version: 0.16.2
Summary: Python Library for Interacting with the 0bsnetwork
Home-page: http://github.com/0bsnetwork/zbspy
Author: James Hitchcock
Author-email: james@0bsnetwork.com
License: MIT
Keywords: 0bsnetwork,blockchain,analytics
Platform: UNKNOWN
Requires-Dist: base58 (==0.2.5)
Requires-Dist: pyblake2
Requires-Dist: python-axolotl-curve25519
Requires-Dist: requests
